oiplot/__init__.py
oiplot/colors.py
oiplot/io.py
oiplot/oifits.py
oiplot/orbit.py
oiplot/shapes.py
oiplot/utils.py
oiplot/config/columns.yaml
oiplot/config/prefixes.npy
oiplot-1.5.2.dist-info/licenses/LICENSE
oiplot-1.5.2.dist-info/METADATA
oiplot-1.5.2.dist-info/WHEEL
oiplot-1.5.2.dist-info/top_level.txt
oiplot-1.5.2.dist-info/RECORD
