Metadata-Version: 2.4
Name: oiplot
Version: 1.5.2
Summary: A plotting tool for OIFITS files with some additional functionality.
Author-email: Marten Scheuck <code@mbscheuck.com>
Project-URL: repository, https://codeberg.org/MBSck/oiplot.git
Requires-Python: >=3.10
License-File: LICENSE
Requires-Dist: astropy>=6.1.7
Requires-Dist: matplotlib>=3.10.1
Requires-Dist: numpy>=2.2.3
Requires-Dist: pandas>=2.2.3
Requires-Dist: pillow>=11.1.0
Requires-Dist: pyyaml>=6.0.2
Requires-Dist: scienceplots>=2.1.1
Requires-Dist: tqdm>=4.67.1
Dynamic: license-file
